spencerbootstrap/__init__.py
spencerbootstrap/bootstrap.py
spencerbootstrap-0.1.dist-info/METADATA
spencerbootstrap-0.1.dist-info/WHEEL
spencerbootstrap-0.1.dist-info/top_level.txt
spencerbootstrap-0.1.dist-info/RECORD
