Metadata-Version: 2.1
Name: spencerbootstrap
Version: 0.1
Summary: The bootstrap porgram using arch.bootstrap
Home-page: https://github.com/Soclemens/bootStrapSpencer
Author: Spencer Clemens
Author-email: Spencer.clemens@usu.edu
License: UNKNOWN
Platform: UNKNOWN
